README.rst
setup.py
pfycat/__init__.py
pfycat.egg-info/PKG-INFO
pfycat.egg-info/SOURCES.txt
pfycat.egg-info/dependency_links.txt
pfycat.egg-info/requires.txt
pfycat.egg-info/top_level.txt