Metadata-Version: 1.1
Name: pfycat
Version: 0.1.0
Summary: python wrapper for gfycat
Home-page: https://gitlab.com/wotanii/pfycat
Author: wotaini
Author-email: pypi@wotanii.de
License: UNKNOWN
Platform: UNKNOWN
Classifier: Development Status :: 4 - Beta
Classifier: Intended Audience :: Developers
Classifier: Topic :: Software Development :: Libraries :: Python Modules
